python_ecd/__init__.py
python_ecd/cli.py
python_ecd/templates/.gitignore.tpl
python_ecd/templates/README.md.tpl
python_ecd/templates/solution.py.tpl
python_ecd/utils.py
python_ecd/version.py
python_ecd-0.2.3.dist-info/WHEEL
python_ecd-0.2.3.dist-info/entry_points.txt
python_ecd-0.2.3.dist-info/METADATA
python_ecd-0.2.3.dist-info/RECORD
