Metadata-Version: 2.3
Name: python-ecd
Version: 0.2.3
Summary: Python CLI for Everybody Codes
Author: Pablo Garcia
Author-email: Pablo Garcia <pablofueros@gmail.com>
Classifier: Programming Language :: Python :: 3.13
Classifier: License :: OSI Approved :: MIT License
Requires-Dist: everybody-codes-data==0.4
Requires-Dist: python-dotenv>=1.2.1
Requires-Dist: typer>=0.20.0
Requires-Python: >=3.13
